{
  "grade": "高二上册",
  "Unit 1 People of Achievement": {
    "chief": "首席的；主要的；首领；长官",
    "poison": "毒药；毒害；下毒；毒害",
    "cure": "治愈；痊愈；治疗；疗法",
    "blunt": "钝的；直言不讳的",
    "botanical": "植物学的",
    "evaluate": "评价；评估",
    "property": "特性；性质；财产",
    "extract": "提取；提炼；摘录；提取物",
    "worm": "蠕虫；寄生虫",
    "substance": "物质；物品；事实",
    "insist": "坚持；强调",
    "insist on": "坚持；坚决要求",
    "scientific": "科学的",
    "consequence": "结果；后果；重要性",
    "apart from": "除……之外；此外",
    "acknowledge": "承认；感谢",
    "apparently": "显然；显而易见地",
    "passive": "被动的；消极的",
    "genius": "天才；天赋；天才人物",
    "perseverance": "毅力；韧性；不屈不挠",
    "radiation": "辐射；放射线",
    "remarkable": "非凡的；显著的；引人注目的",
    "vital": "至关重要的；生死攸关的",
    "commit": "犯；做错事；承诺",
    "commit oneself to": "致力于；献身于",
    "compulsory": "义务的；强制的",
    "objective": "目标；目的；客观的",
    "pursuit": "追求；工作；职业",
    "physician": "医师；内科医生",
    "distinguish": "区分；辨别；使杰出",
    "infer": "推断；暗示",
    "scientifically": "合乎科学地"
  },
  "Unit 2 Looking into the Future": {
    "automatic": "自动的；无意识的",
    "automatically": "自动地；机械地",
    "artificial": "人造的；人工的；假的",
    "artificial intelligence": "人工智能",
    "perspective": "态度；观点；透视画法",
    "textile": "纺织品；纺织的",
    "profession": "职业；行业；声明",
    "occupation": "职业；占有；消遣",
    "employ": "使用；雇佣；使忙于",
    "emerge": "出现；浮现；暴露",
    "chest": "胸部；衣柜；箱子",
    "calculate": "计算；估计；计划",
    "predict": "预言；预测；预报",
    "oppose": "反对；对抗；抗争",
    "oppose doing": "反对做某事",
    "resist": "抵抗；抗拒；忍耐",
    "advocate": "提倡；拥护；主张；倡导者",
    "hence": "因此；今后",
    "critical": "批评的；爱挑剔的；关键的",
    "potential": "潜在的；可能的；潜力",
    "energy-consuming": "耗能的",
    "reform": "改革；改良；改正",
    "decrease": "减少；减小；降低",
    "accelerate": "加速；促进；增加",
    "protest": "抗议；声明；断言",
    "urban": "城市的；都市的",
    "consumer": "消费者；用户；顾客",
    "remove": "移开；拿开；去掉",
    "replace": "取代；替换；代替",
    "facility": "设施；设备；容易",
    "telecom": "电信；远程通信",
    "detect": "察觉；发现；探测"
  },
  "Unit 3 Food and Culture": {
    "cuisine": "烹饪；菜肴；风味",
    "precious": "珍贵的；宝贵的",
    "stew": "炖；炖汤；焖",
    "bacon": "咸肉；熏肉",
    "handmade": "手工的；人造的",
    "chili": "辣椒；辣椒粉",
    "garlic": "大蒜；蒜头",
    "onion": "洋葱；洋葱头",
    "lemon": "柠檬",
    "roast": "烤；烘；烘烤的",
    "fry": "油炸；油煎；油炒",
    "stable": "稳定的；牢固的；马厩",
    "exception": "例外；异议",
    "dine": "进餐；用餐；宴请",
    "dine out": "外出就餐",
    "cutlery": "餐具；刀叉",
    "cafeteria": "自助餐厅；食堂",
    "quantity": "量；数量；大量",
    "ideal": "理想的；完美的；理想",
    "fund": "基金；资金；存款",
    "modest": "谦虚的；适度的；端庄的",
    "recipe": "食谱；处方；秘诀",
    "beverage": "饮料",
    "sour": "酸的；发酵的；刺耳的",
    "consume": "消耗；消费；大吃大喝",
    "suggestion": "建议；示意；微量",
    "nutritious": "有营养的；滋养的",
    "balanced": "平衡的；和谐的",
    "diet": "饮食；食物；节食",
    "whichever": "无论哪个；任何一个",
    "elegant": "高雅的；优雅的；讲究的",
    "cater": "迎合；满足需求；提供饮食"
  },
  "Unit 4 Journey Across a Land": {
    "vast": "广阔的；巨大的；大量的",
    "frost": "霜；霜冻；结霜",
    "grand": "宏伟的；豪华的；极重要的",
    "territory": "领土；领域；范围",
    "port": "港口；口岸",
    "merchant": "商人；批发商；商业的",
    "thick": "厚的；浓的；粗大的",
    "freezing": "冰冷的；严寒的；冻结",
    "curtain": "窗帘；门帘；幕布",
    "border": "边界；边境；国界",
    "edge": "边缘；优势；刀刃",
    "valley": "山谷；溪谷；流域",
    "rail": "铁轨；栏杆；铁路",
    "railway": "铁路；铁道",
    "scenery": "风景；景色；舞台布景",
    "awesome": "令人敬畏的；极好的",
    "spectacular": "壮观的；惊人的；奇观",
    "peak": "山峰；最高点；最高的",
    "slope": "斜坡；倾斜；斜率",
    "route": "路线；航线；通道",
    "destination": "目的地；终点",",
    "crew": "队；组；全体人员",
    "aboard": "在飞机上；在船上；在火车上",
    "sleigh": "雪橇；乘雪橇",
    "antique": "古老的；古董的；古董",
    "preparation": "准备；预备；准备工作",
    "prepare": "准备；预备；使适合",
    "geographical": "地理的；地理学的",
    "flat": "平的；单调的；公寓",
    "highway": "公路；大路；主干道",
    "expanse": "宽阔；广阔的区域",
    "bless": "祝福；保佑；赞美"
  },
  "Unit 5 First Aid": {
    "unconscious": "无意识的；失去知觉的",
    "choke": "窒息；噎住；窒息",
    "bleed": "流血；出血；渗出",
    "panicked": "惊慌失措的",
    "temporary": "暂时的；临时的",
    "injury": "伤害；损害；受伤处",
    "bleeding": "出血；流血",
    "sprain": "扭伤",
    "ankle": "踝关节；脚踝",
    "rib": "肋骨；排骨",
    "modest": "适度的；谦虚的；端庄的",
    "interrupt": "打断；中断；插嘴",
    "urgent": "紧急的；急迫的",
    "urge": "力劝；催促；强烈欲望",
    "fracture": "骨折；破裂；断裂",
    "smell": "气味；嗅觉；闻到",
    "radiation": "辐射；放射线",
    "mild": "温和的；轻微的；淡味的",
    "severely": "严重地；严格地",
    "swell": "肿胀；膨胀；隆起",
    "blister": "水泡；起泡",
    "nerve": "神经；勇气；胆量",
    "bandage": "绷带；用绷带包扎",
    "kettle": "水壶；罐",
    "pour": "倒；灌；倾泻；流出",
    "raw": "生的；未加工的；生疏的",
    "ice pack": "冰袋；冰包",
    "tight": "紧的；密封的；绷紧的",
    "loose": "宽松的；散漫的；不牢固的",
    "wipe": "擦；消除；涂上；擦拭",
    "infection": "感染；传染；影响",
    "vital": "至关重要的；生死攸关的",
    "symptom": "症状；征兆",
    "determine": "确定；决定；判定",
    "treat": "治疗；对待；探讨；请客",
    "discharge": "排出；释放；解雇；卸下"
  }
}